cdk_klayers/__init__.py
cdk_klayers/exceptions.py
cdk_klayers/klayers.py
cdk_klayers-0.3.0.dist-info/METADATA
cdk_klayers-0.3.0.dist-info/WHEEL
cdk_klayers-0.3.0.dist-info/RECORD
