Metadata-Version: 2.1
Name: cdk-klayers
Version: 0.3.0
Summary: 
Author: Keith Rozario
Author-email: keithjosephrozario@gmail.com
Requires-Python: >=3.8,<4.0
Classifier: Programming Language :: Python :: 3
Classifier: Programming Language :: Python :: 3.8
Classifier: Programming Language :: Python :: 3.9
Classifier: Programming Language :: Python :: 3.10
Classifier: Programming Language :: Python :: 3.11
Classifier: Programming Language :: Python :: 3.12
Requires-Dist: aws-cdk-lib (>=2.137.0,<3.0.0)
Requires-Dist: requests (>=2.31.0,<3.0.0)
